tjcloud/__init__.py
tjcloud/_modidx.py
tjcloud/linode.py
tjcloud-3.0.0.dist-info/METADATA
tjcloud-3.0.0.dist-info/WHEEL
tjcloud-3.0.0.dist-info/entry_points.txt
tjcloud-3.0.0.dist-info/RECORD
