Metadata-Version: 2.1
Name: tjcloud
Version: 3.0.0
Summary: TJ Palanca Personal Cloud
Home-page: https://tjpalanca.com/tjcloud
License: AGPL-3.0
Author: TJ P
Author-email: code@tjpalanca.com
Requires-Python: >=3.11,<4.0
Classifier: License :: OSI Approved :: GNU Affero General Public License v3
Classifier: Programming Language :: Python :: 3
Classifier: Programming Language :: Python :: 3.11
Requires-Dist: requests (>=2.28.1,<3.0.0)
Project-URL: Documentation, https://tjpalanca.com/tjcloud
Project-URL: Repository, https://github.com/tjpalanca/tjcloud.git
